PerfectMaze/HilbertMaze.py
PerfectMaze/__init__.py
PerfectMaze/utils.py
perfectmaze-0.0.1.dist-info/METADATA
perfectmaze-0.0.1.dist-info/WHEEL
perfectmaze-0.0.1.dist-info/top_level.txt
perfectmaze-0.0.1.dist-info/RECORD
