Metadata-Version: 2.4
Name: PerfectMaze
Version: 0.0.1
Author-email: "星灿长风v(StarWindv)" <starwindv.stv@gmail.com>
License: GPLv3
Project-URL: Homepage, https://github.com/StarWindv/PerfectMaze
Classifier: Programming Language :: Python :: 3
Requires-Python: >=3.10
Requires-Dist: rich
Requires-Dist: numpy
Requires-Dist: matplotlib
